govtech_csg_xcg/securemodelpkid/__init__.py
govtech_csg_xcg/securemodelpkid/apps.py
govtech_csg_xcg/securemodelpkid/helpers.py
govtech_csg_xcg/securemodelpkid/model.py
govtech_csg_xcg_securemodelpkid-0.1.0.dist-info/LICENSE
govtech_csg_xcg_securemodelpkid-0.1.0.dist-info/METADATA
govtech_csg_xcg_securemodelpkid-0.1.0.dist-info/WHEEL
govtech_csg_xcg_securemodelpkid-0.1.0.dist-info/top_level.txt
govtech_csg_xcg_securemodelpkid-0.1.0.dist-info/RECORD
