Metadata-Version: 2.1
Name: govtech-csg-xcg-securemodelpkid
Version: 0.1.0
Summary: Module that provides interfaces for DB models that transparently generates a more secure random string as the primary key/ID.
Project-URL: Homepage, https://xcg.tech.gov.sg
Project-URL: Documentation, https://xcg.tech.gov.sg
Project-URL: Repository, https://github.com/GovTech-CSG/govtech-csg-xcg-securemodelpkid
Classifier: Development Status :: 4 - Beta
Classifier: License :: OSI Approved :: Mozilla Public License 2.0 (MPL 2.0)
Requires-Python: >=3.8
License-File: LICENSE
Requires-Dist: django ~=4.1
